moshier_ephemeris/__init__.py
moshier_ephemeris/py.typed
moshier_ephemeris-0.1.0.dist-info/WHEEL
moshier_ephemeris-0.1.0.dist-info/METADATA
moshier_ephemeris-0.1.0.dist-info/RECORD
