Metadata-Version: 2.4
Name: moshier-ephemeris
Version: 0.1.0
Summary: Pure Python Implementation of Moshier Ephemeris
Author: Kelvin Ng
Author-email: Kelvin Ng <hoishing@gmail.com>
License-Expression: MIT
Requires-Python: >=3.12
